gitwithtea_py/__init__.py
gitwithtea_py/api/__init__.py
gitwithtea_py/api/activitypub_api.py
gitwithtea_py/api/admin_api.py
gitwithtea_py/api/issue_api.py
gitwithtea_py/api/miscellaneous_api.py
gitwithtea_py/api/notification_api.py
gitwithtea_py/api/organization_api.py
gitwithtea_py/api/package_api.py
gitwithtea_py/api/repository_api.py
gitwithtea_py/api/settings_api.py
gitwithtea_py/api/user_api.py
gitwithtea_py/api_client.py
gitwithtea_py/configuration.py
gitwithtea_py/models/__init__.py
gitwithtea_py/models/access_token.py
gitwithtea_py/models/activity_pub.py
gitwithtea_py/models/add_collaborator_option.py
gitwithtea_py/models/add_time_option.py
gitwithtea_py/models/annotated_tag.py
gitwithtea_py/models/annotated_tag_object.py
gitwithtea_py/models/api_error.py
gitwithtea_py/models/attachment.py
gitwithtea_py/models/branch.py
gitwithtea_py/models/branch_protection.py
gitwithtea_py/models/changed_file.py
gitwithtea_py/models/combined_status.py
gitwithtea_py/models/comment.py
gitwithtea_py/models/commit.py
gitwithtea_py/models/commit_affected_files.py
gitwithtea_py/models/commit_date_options.py
gitwithtea_py/models/commit_meta.py
gitwithtea_py/models/commit_stats.py
gitwithtea_py/models/commit_status.py
gitwithtea_py/models/commit_status_state.py
gitwithtea_py/models/commit_user.py
gitwithtea_py/models/contents_response.py
gitwithtea_py/models/create_access_token_option.py
gitwithtea_py/models/create_branch_protection_option.py
gitwithtea_py/models/create_branch_repo_option.py
gitwithtea_py/models/create_email_option.py
gitwithtea_py/models/create_file_options.py
gitwithtea_py/models/create_fork_option.py
gitwithtea_py/models/create_gpg_key_option.py
gitwithtea_py/models/create_hook_option.py
gitwithtea_py/models/create_hook_option_config.py
gitwithtea_py/models/create_issue_comment_option.py
gitwithtea_py/models/create_issue_option.py
gitwithtea_py/models/create_key_option.py
gitwithtea_py/models/create_label_option.py
gitwithtea_py-0.1.1.dist-info/METADATA
gitwithtea_py-0.1.1.dist-info/WHEEL
gitwithtea_py-0.1.1.dist-info/RECORD
