Metadata-Version: 2.1
Name: gitwithtea-py
Version: 0.1.1
Summary: Gitea API wrapper in Python
Home-page: https://codeberg.org/gitwithtea-py/gitwithtea_py
License: GPL-3.0-or-later
Keywords: gitea,tea,git,api,forgejo,python,swagger
Author: 0xMRTT
Author-email: 0xMRTT@proton.me
Maintainer: 0xMRTT
Maintainer-email: 0xMRTT@proton.me
Requires-Python: >=3.10,<4.0
Classifier: Development Status :: 3 - Alpha
Classifier: Intended Audience :: Developers
Classifier: License :: OSI Approved :: GNU General Public License v3 or later (GPLv3+)
Classifier: Operating System :: POSIX :: Linux
Classifier: Programming Language :: Python
Classifier: Programming Language :: Python :: 3
Classifier: Programming Language :: Python :: 3.10
Classifier: Programming Language :: Python :: 3.11
Classifier: Topic :: Software Development :: Libraries :: Python Modules
Classifier: Topic :: Utilities
Requires-Dist: certifi (>=2023.5.7,<2024.0.0)
Requires-Dist: python-dateutil (>=2.8.2,<3.0.0)
Requires-Dist: setuptools (>=67.8.0,<68.0.0)
Requires-Dist: six (>=1.16.0,<2.0.0)
Requires-Dist: urllib3 (>=2.0.2,<3.0.0)
Project-URL: Bug Tracker, https://codeberg.org/gitwithtea-py/gitwithtea_py/issues
Project-URL: Documentation, https://codeberg.org/gitwithtea-py/gitwithtea_py
Project-URL: Repository, https://codeberg.org/gitwithtea-py/gitwithtea_py
